{
	"info": {
		"site_url": "http://martineau.tv",
		"site_name": "Zander",
		"name": "Zander Martineau",
		"first_name": "Zander",
		"tagline": "I am a London-based Creative Technologist working at <a href=\"http://tmw.co.uk\">TMW</a>."
	},
	"portfolio": [
		{
			"name": "Lynx Africa 18th Anniversary",
			"description": "<p>The iconic Lynx Africa deoderant turns 18 this year and to celebrate I helped produce a Tumblr blog that publishes a new piece of artwork each day for 18 days.</p>",
			"view": {
				"name": "lynxafrica18.tumblr.com",
				"url": "http://lynxafrica18.tumblr.com"
			},
			"date": "October 2013",
			"skills": "Front-end development",
			"credits": [
				{
					"title": "Designer",
					"name": "Andrew Turk"
				},
				{
					"title": "Agency",
					"name": "TMW",
					"url": "http://tmw.co.uk"
				},
				{
					"title": "Client",
					"name": "Unilever",
					"url": "http://unilever.com"
				}
			],
			"images": [
				{
					"caption": "",
					"url": "jimll.jpg"
				}
			],
			"meta": {
				"name" : "lynxafrica",
				"id": "13",
				"layout": "stacked",
				"type": "website",
				"colours": {
					"bg": "#00723B",
					"text": "#fff",
					"link": "#fff",
					"linkHover": "#fff"
				}
			}
		},
		{
			"name": "TMW Kickoff",
			"description": "<p>Kickoff is a robust, adaptable and unopinionated front-end framework that is great starting point for any web site; we use for every project at TMW.</p><p>The framework includes a SASS-based, CSS framework (with all the usual resets and mixins), a responsive <a href=\"https://github.com/mrmartineau/Choreographic-Grid\">grid system</a>; beautiful typographic styles; javascript plugins, utilities and a great set of boilerplates for most eventualities. This means that our devs can get up and running as quickly as possible and not have to worry about this tedious initial step.</p>",
			"view": {
				"name": "github.com/mrmartineau/kickoff",
				"url": "http://github.com/mrmartineau/kickoff"
			},
			"date": "Ongoing",
			"skills": "Front-end",
			"credits": [
				{
					"title": "Developer",
					"name": "Zander Martineau"
				},
				{
					"title": "Developer",
					"name": "Ashley Nolan",
					"url": "http://dragongraphics.co.uk"
				},
				{
					"title": "Agency",
					"name": "TMW",
					"url": "http://tmw.co.uk"
				}
			],
			"meta": {
				"name" : "kickoff",
				"id": "2",
				"layout": "",
				"type": "code",
				"colours": {
					"bg": "#96C3AC",
					"text": "#1e4833",
					"link": "#F6EEDD",
					"linkHover": "#fff"
				}
			},
			"github": {
				"user": "tmwagency",
				"repo": "kickoff"
			}
		},
		{
			"name": "The Bar",
			"description": "<p>theBar.com is a popular US cocktail resource; I was a member of the team who created the Western Europe version of this already popular site.</p><p>From UX to performance, every aspect of the site was improved and carefully considered. I created a special asset font for the site, this creates crisp, hiDpi friendly icons that look great at any resolution.</p>",
			"view": {
				"name": "uk.thebar.com",
				"url": "http://uk.thebar.com"
			},
			"date": "February - September 2013",
			"skills": "Front-end development; asset font creation, hiDPI",
			"credits": [
				{
					"title": "Designer",
					"name": "Simon Kinslow",
					"url": "http://www.simonkinslow.com/"
				},
				{
					"title": "Dev (F/E)",
					"name": "Nic Bell",
					"url": "http://nicbell.net/"
				},
				{
					"title": "Dev (B/E)",
					"name": "Martin Georgiev",
					"url": "http://www.linkedin.com/profile/view?id=17683453"
				},
				{
					"title": "Dev (B/E)",
					"name": "Matthew Basson",
					"url": "http://www.linkedin.com/profile/view?id=50420509"
				},
				{
					"title": "Agency",
					"name": "TMW",
					"url": "http://tmw.co.uk"
				},
				{
					"title": "Client",
					"name": "Diageo",
					"url": "http://diageo.com"
				}
			],
			"images": [
				{
					"caption": "",
					"shot": "desktop",
					"url": "01.png"
				},
				{
					"caption": "",
					"shot": "mobile",
					"url": "02.png"
				}
			],
			"meta": {
				"name" : "thebar",
				"id": "12",
				"layout": "responsive",
				"type": "website",
				"colours": {
					"bg": "#031962",
					"text": "#fff",
					"link": "#F12EA1",
					"linkHover": "#fff"
				}
			}
		},
		{
			"name": "Lynx Apollo Vote Boosters",
			"description": "<p>Lynx is currently (Jan 2013) running a worldwide competition to send someone into space - the entrant with the most votes wins - they asked TMW to create a microsite to help entrants promote themselves and garner more votes.</p><p>We built a responsive, single-page app that allows entrants to create and share a poster or choose from one of many prewritten status messages. The site is interesting because it positions the user in space and changes the viewport on each sub-page. As well as being project lead, I created the moving page navigation element and the more complex responsive features.</p>",
			"view": {
				"name": "lsa.lynxeffect.com/booster/",
				"url": "http://lsa.lynxeffect.com/booster/"
			},
			"date": "December 2012 - Jan 2013",
			"skills": "Front-end: responsive, social APIs",
			"credits": [
				{
					"title": "Designer",
					"name": "Andrew Jordan",
					"url": "http://doesign.co.uk/"
				},
				{
					"title": "Developer",
					"name": "Nic Bell",
					"url": "http://nicbell.net/"
				},
				{
					"title": "Developer",
					"name": "Ivan Hayes",
					"url": "https://twitter.com/munkychop"
				},
				{
					"title": "Agency",
					"name": "TMW",
					"url": "http://tmw.co.uk"
				},
				{
					"title": "Brand",
					"name": "Lynx",
					"url": "http://lynxeffect.co.uk"
				},
				{
					"title": "Client",
					"name": "Unilever",
					"url": "http://unilever.co.uk"
				}
			],
			"images": [
				{
					"caption": "",
					"url": "02.jpg"
				},
				{
					"caption": "",
					"url": "01.jpg"
				},
				{
					"caption": "",
					"url": "03.jpg"
				}
			],
			"meta": {
				"name" : "lynx-apollo",
				"id": "11",
				"layout": "desktop-three-up",
				"type": "website",
				"colours": {
					"bg": "#031962",
					"text": "#fff",
					"link": "#F12EA1",
					"linkHover": "#fff"
				}
			}
		},
		{
			"name": "Brother Printers",
			"description": "<p>Brother Printers asked TMW to create a microsite for the various printer ranges. Each page of this site is devoted to one range and uses campaign assets to give a more consistent look and feel across media.</p><p>I worked closely with the designer, Dawn Jenner, to create an engaging and appealing experience that promoted each product's features and enabled customers to make a more informed decision.</p>",
			"view": {
				"name": "campaigns.brother.co.uk",
				"url": "http://campaigns.brother.co.uk"
			},
			"date": "September 2012 - Jan 2013",
			"skills": "Front-end: parallax, performance",
			"credits": [
				{
					"title": "Designer",
					"name": "Dawn Jenner"
				},
				{
					"title": "Agency",
					"name": "TMW",
					"url": "http://tmw.co.uk"
				},
				{
					"title": "Client",
					"name": "Brother Industries",
					"url": "http://brother.co.uk"
				}
			],
			"images": [
				{
					"caption": "",
					"url": "02.jpg"
				},
				{
					"caption": "",
					"url": "01.jpg"
				},
				{
					"caption": "",
					"url": "03.jpg"
				}
			],
			"meta": {
				"name"  : "brother-campaigns",
				"id"    : "11",
				"layout": "desktop-three-up",
				"type"  : "website",
				"colours": {
					"bg": "#031962",
					"text": "#fff",
					"link": "#F12EA1",
					"linkHover": "#fff"
				},
				"tags": [
					""
				]
			}
		},
		{
			"name": "Knorr Mobile",
			"description": "<p>Knorr, the food and beverage company, needed a mobile site for their successful corporate presence in the UK, TMW were asked to create it for them.</p><p>I developed a simple, hiDPI ready, site as a counterpart to their desktop site that, that focused on performance and</p>",
			"view": {
				"name": "knorr.co.uk",
				"url": "http://knorr.co.uk"
			},
			"date": "August 2012",
			"skills": "Front-end: templating, javascript, AJAX",
			"credits": [
				{
					"title": "Designer",
					"name": "Hannah Ormsby",
					"url": "http://hanormsby.co.uk"
				},
				{
					"title": "Developer",
					"name": "Tim Coppinger"
				},
				{
					"title": "Agency",
					"name": "TMW",
					"url": "http://tmw.co.uk"
				}
			],
			"images": [
				{
					"caption": "",
					"url": "01.jpg"
				},
				{
					"caption": "",
					"url": "02.jpg"
				}
			],
			"meta": {
				"name" : "knorr-mobile",
				"id": "10",
				"layout": "mobile-two-up",
				"type": "website",
				"colours": {
					"bg": "#009242",
					"text": "#fff",
					"link": "#F6DA3F",
					"linkHover": "#fff"
				},
				"tags": [
					"mobile"
				]
			}
		},
		{
			"name": "DrinkIQ",
			"description": "<p>This app, developed for <a href=\"http://drinkiq.com\">DrinkIQ</a>, determines how many calories and units of alcohol you might have consumed.</p><p>It is a fully responsive site that features two very different layouts at each of the main breakpoints. Javascript templating by <a href=\"http://handlebarsjs.com/\">Handlebars</a> is used to populate the site's content.</p>",
			"view": {
				"name": "calculator.drinkiq.com",
				"url": "http://calculator.drinkiq.com"
			},
			"date": "June 2012",
			"skills": "Front-end",
			"credits": [
				{
					"title": "Designer",
					"name": "Sam Cottrell"
				},
				{
					"title": "Developer",
					"name": "Matt Basson"
				},
				{
					"title": "Agency",
					"name": "TMW",
					"url": "http://tmw.co.uk"
				},
				{
					"title": "Client",
					"name": "Diageo",
					"url": "http://diageo.com"
				}
			],
			"images": [
				{
					"caption": "",
					"shot": "desktop",
					"url": "01.jpg"
				},
				{
					"caption": "",
					"shot": "mobile",
					"url": "02.jpg"
				}
			],
			"meta": {
				"name" : "drinkiq",
				"id": "8",
				"layout": "responsive",
				"type": "website",
				"colours": {
					"bg": "#96C3AC",
					"text": "#1e4833",
					"link": "#F6EEDD",
					"linkHover": "#fff"
				},
				"bg": "",
				"tags": [
					""
				]
			}
		},
		{
			"name": "Novalux Energy website",
			"description": "<p>Novalux's <a href=\"#/projects/6/\">visual identity</a> helped form the basis for their website design. I also designed the site and developed it using the <a href=\"http://expressionengine.com\">ExpressionEngine</a> CMS. It makes use of some great web fonts (served from <a href=\"http://fontdeck.com\">Fontdeck</a>), it is set in <a href=\"http://www.ms-studio.com/FontSales/proximanova.html\">Proxima Nova</a> and <a href=\"http://fontdeck.com/font/clarendonurw/light\">Clarendon</a>.</p>",
			"view": {
				"name": "novaluxenergy.com",
				"url": "http://novaluxenergy.com/"
			},
			"date": "March 2012",
			"skills": "Design, Front-end, Back-end",
			"credits": [
				{
					"title": "Client",
					"name": "Novalux",
					"url": "http://novaluxenergy.com"
				}
			],
			"images": [
				{
					"caption": "",
					"url": "01.jpg"
				}
			],
			"meta": {
				"name" : "novalux",
				"id": "6",
				"layout": "stacked",
				"type": "website",
				"colours": {
					"bg": "#0D204A",
					"text": "#fff",
					"link": "#0D9B8C",
					"linkHover": "#fff"
				},
				"tags": [
					""
				]
			}
		},
		{
			"name": "Novalux Energy Solutions visual identity",
			"description": "<p>Novalux Energy Solutions are experts in providing renewable and cost-effective energy solutions to businesses across the world. I was given the task of creating the Novalux visual identity.</p>",
			"view": {
				"name": "novaluxenergy.com",
				"url": "http://novaluxenergy.com/"
			},
			"date": "March 2012",
			"skills": "Design",
			"credits": [
				{
					"title": "Client",
					"name": "Novalux",
					"url": "http://novaluxenergy.com"
				}
			],
			"images": [
				{
					"caption": "Logo on light background",
					"url": "01.jpg"
				},
				{
					"caption": "Logo on dark background",
					"url": "02.jpg"
				}
			],
			"meta": {
				"name" : "novalux-logo",
				"id": "5",
				"layout": "stacked",
				"type": "logo",
				"colours": {
					"bg": "#0D204A",
					"text": "#fff",
					"link": "#0D9B8C",
					"linkHover": "#fff"
				},
				"tags": [
					""
				]
			}
		},
		{
			"name": "Datasift UI & iconography",
			"description": "<p>DataSift is the leading platform for building applications with insights derived from the most popular social networks and news sources. NEVERBLAND were asked to create a WYSIWYG editor for customers to more easily create 'streams' within their system.</p> <p>I designed a huge library of icons and the UI for the WYSIWYG editor itself. I left NEVERBLAND half-way through this project so what you see now is an updated version of the work that I did.</p>",
			"view": {
				"name": "datasift.com",
				"url": "http://datasift.com"
			},
			"date": "January 2012",
			"skills": "Design",
			"credits": [
				{
					"title": "Agency",
					"name": "NEVERBLAND",
					"url": "http://neverbland.com"
				},
				{
					"title": "Client",
					"name": "Datasift",
					"url": "http://datasift.com"
				}
			],
			"images": [
				{
					"caption": "UI",
					"url": "01.jpg"
				},
				{
					"caption": "Icon spritesheet",
					"url": "02.gif"
				}
			],
			"meta": {
				"name" : "datasift",
				"id": "4",
				"layout": "desktop-two-up",
				"type": "website",
				"colours": {
					"bg": "#96C3AC",
					"text": "#1e4833",
					"link": "#F6EEDD",
					"linkHover": "#fff"
				},
				"tags": [
					""
				]
			}
		},
		{
			"name": "Colette",
			"description": "<p>Colette is a department store based in Paris. NEVERBLAND were asked to pitch for a redesign of their existing ecommerce offering.</p><p>I produced this design for the home page, you can see three states: normal, navigation hovered and page content hovered. Unfortunately our ideas were not chosen and at time of writing, Colette still have not redesigned their site.</p>",
			"view": {
				"name": "Pitch"
			},
			"date": "June 2011",
			"skills": "Design",
			"credits": [
				{
					"title": "Agency",
					"name": "NEVERBLAND",
					"url": "http://neverbland.com"
				},
				{
					"title": "Client",
					"name": "Colette",
					"url": "http://colette.fr"
				}
			],
			"images": [
				{
					"caption": "Homepage: item hover",
					"url": "01.jpg"
				}
			],
			"meta": {
				"name" : "colette",
				"id": "3",
				"layout": "stacked",
				"type": "website",
				"colours": {
					"bg": "#96C3AC",
					"text": "#1e4833",
					"link": "#F6EEDD",
					"linkHover": "#fff"
				},
				"tags": [
					"pitch"
				]
			}
		},
		{
			"name": "Shift 4",
			"description": "<p>Shift 4 are a broadcast facility company for film and TV in the UK. NEVERBLAND were asked to revamp and extend their existing site. We added a full equipment listing, with wishlist (think shopping list) feature; a blog and various other sections that overall helped customers engage with the company.</p><p>I designed & developed the front-end for this project making it fully responsive & adaptable to any device that uses it.</p>",
			"view": {
				"name": "shift-4.co.uk",
				"url": "http://shift-4.co.uk"
			},
			"date": "October 2011",
			"skills": "Design and front-end development",
			"credits": [
				{
					"title": "Developer",
					"name": "Maciej Garycki"
				},
				{
					"title": "Agency",
					"name": "NEVERBLAND",
					"url": "http://neverbland.com"
				}
			],
			"images": [
				{
					"caption": "Homepage: desktop",
					"shot": "desktop",
					"url": "desktop.png"
				},
				{
					"caption": "Homepage: mobile",
					"shot": "mobile",
					"url": "mobile.png"
				}
			],
			"meta": {
				"name" : "shift-4",
				"id": "2",
				"layout": "responsive",
				"type": "website",
				"colours": {
					"bg": "#FE0C24",
					"text": "#fff",
					"link": "#000",
					"linkHover": "#fff"
				},
				"tags": [
					""
				]
			}
		},
		{
			"name": "Conversocial",
			"description": "<p>Conversocial is a Social Media management app for marketers and brands. NEVERBLAND were asked to redesign & develop their existing website. What you see below is my design for their home page, which unfortunately, was never used, however, many aspects were used in the final site. Conversocial have since redesigned their homepage so NEVERBLAND's version can be seen <a href=\"http://web.archive.org/web/20110705083639/http://www.conversocial.com/\">here</a>.</p>",
			"view": {
				"url": "http://conversocial.com",
				"name": "conversocial.com"
			},
			"date": "January 2011",
			"skills": "Design",
			"credits": [
				{
					"title": "Agency",
					"name": "NEVERBLAND",
					"url": "http://neverbland.com"
				}
			],
			"images": [
				{
					"url": "01.jpg"
				}
			],
			"meta": {
				"name" : "conversocial",
				"id": "1",
				"layout": "stacked",
				"type": "website",
				"colours": {
					"bg": "#4A9BDC",
					"text": "#fff",
					"link": "#000",
					"linkHover": "#fff"
				},
				"tags": [
					""
				]
			}
		},
		{
			"name": "Soho Fixed",
			"description": "<p>Soho Fixed is a site where you can buy custom-made, fixed-gear or single-speed bycycles. I designed and developed the entire project - pay attention to the header with it's animating background image and the hover effect on the navigation. All non-bike photography was also shot by me.</p>",
			"view": {
				"url": "http://sohofixed.com",
				"name": "sohofixed.com"
			},
			"date": "January 2011",
			"skills": "Design & Development",
			"credits": [
				{
					"title": "Agency",
					"name": "NEVERBLAND",
					"url": "http://neverbland.com"
				}
			],
			"images": [
				{
					"url": "01.jpg"
				}
			],
			"meta": {
				"name" : "sohofixed",
				"id": "1",
				"layout": "stacked",
				"type": "website",
				"colours": {
					"bg": "#4A9BDC",
					"text": "#fff",
					"link": "#000",
					"linkHover": "#fff"
				},
				"tags": [
					""
				]
			}
		},
		{
			"name": "Soho Fixed visual identity",
			"description": "<p>As well as creating the website, I was given the task of creating the Soho Fixed visual identity. I kept it simple and bold because it was for stickers on each bike. The logo can also be separated, for example: the shield can be used on the head tube and the wording on the down tube.</p>",
			"view": {
				"name": "sohofixed.com",
				"url": "http://sohofixed.com/"
			},
			"date": "January 2011",
			"skills": "Design",
			"credits": [
				{
					"title": "Client",
					"name": "Soho Fixed",
					"url": "http://sohofixed.com"
				}
			],
			"images": [
				{
					"caption": "Logo on dark background",
					"url": "01.gif"
				}
			],
			"meta": {
				"name" : "sohofixed-identity",
				"id": "5",
				"layout": "stacked",
				"type": "logo",
				"colours": {
					"bg": "#0D204A",
					"text": "#fff",
					"link": "#0D9B8C",
					"linkHover": "#fff"
				},
				"tags": [
					"logo"
				]
			}
		}
	],
	"open-source": {
		"title" : "Open Source Projects",
		"description": "Below are a few open source projects that I maintain and contribute to.",
		"items": [
			{
				"name": "Social Homepage",
				"description": "<p>My version of a social home page/business card site. You can see it at <a href=\"http://mrmartineau.co.uk\">mrmartineau.co.uk</a>. Please use it for yourself by <a href=\"https://github.com/mrmartineau/social-homepage/fork\">forking the project on Github</a></p>",
				"view": {
					"name": "mrmartineau.github.com/social-homepage",
					"url": "http://mrmartineau.github.com/social-homepage"
				},
				"date": "October 2012",
				"skills": "CSS: SASS",
				"meta": {
					"name" : "social-homepage",
					"id": "4",
					"layout": "",
					"type": "code"
				},
				"github": {
					"user": "mrmartineau",
					"repo": "social-homepage"
				}
			},
			{
				"name": "Sublime Text Setup",
				"description": "<p>This project aims to enable people to get started with Sublime Text 2 much more quickly. It includes a list of recommended plugins and useful defaults for some plugins and settings.</p>",
				"view": {
					"name": "github.com/mrmartineau/SublimeTextSetup",
					"url": "https://github.com/mrmartineau/SublimeTextSetup"
				},
				"date": "Ongoing",
				"meta": {
					"name" : "sublime-text-setup",
					"id": "1",
					"layout": "",
					"type": "code"
				},
				"github": {
					"user": "mrmartineau",
					"repo": "SublimeTextSetup"
				}
			},
			{
				"name": "SASS Snippets",
				"description": "<p>A collection of Sublime Text 2 snippets & functions to be used with SASS. Most snippets are to be used specifically with .scss</p>",
				"view": {
					"name": "github.com/mrmartineau/SASS-Snippets",
					"url": "https://github.com/mrmartineau/SASS-Snippets"
				},
				"date": "Ongoing",
				"meta": {
					"name" : "sass-snippets",
					"id": "1",
					"layout": "",
					"type": "code"
				},
				"github": {
					"user": "mrmartineau",
					"repo": "SASS-Snippets"
				}
			},
			{
				"name": "The Choreographic Grid",
				"description": "<p>A responsive CSS grid for content interdigitation, built with SASS for today's modern websites. Instead of using poorly supported features of modern CSS (I'm looking at you, Flex box), it uses floats but has some sneaky tricks up it's sleeve.</p><p>As well as standard grid features, I created two new features that help when creating responsive sites, these are 'Shunts' and 'Splits'. Find out more at the <a href=\"http://mrmartineau.github.io/Choreographic-Grid/test.html\">project demo</a>.</p>",
				"view": {
					"name": "mrmartineau.github.com/choreographic-grid",
					"url": "http://mrmartineau.github.com/choreographic-grid"
				},
				"date": "October 2012",
				"skills": "CSS: SASS",
				"meta": {
					"name" : "choreographic-grid",
					"id": "3",
					"layout": "",
					"type": "code"
				},
				"github": {
					"user": "mrmartineau",
					"repo": "choreographic-grid"
				}
			},
			{
				"name": "TMW Kickoff",
				"description": "<p>Kickoff is a robust, adaptable and unopinionated front-end framework that is great starting point for any web site; we use for every project at TMW.</p><p>The framework includes a SASS-based, CSS framework (with all the usual resets and mixins), a responsive <a href=\"https://github.com/mrmartineau/Choreographic-Grid\">grid system</a>; beautiful typographic styles; javascript plugins, utilities and a great set of boilerplates for most eventualities. This means that our devs can get up and running as quickly as possible and not have to worry about this tedious initial step.</p>",
				"view": {
					"name": "github.com/mrmartineau/kickoff",
					"url": "http://github.com/mrmartineau/kickoff"
				},
				"date": "Ongoing",
				"skills": "Front-end",
				"credits": [
					{
						"title": "Developer",
						"name": "Zander Martineau"
					},
					{
						"title": "Developer",
						"name": "Ashley Nolan",
						"url": "http://dragongraphics.co.uk"
					},
					{
						"title": "Agency",
						"name": "TMW",
						"url": "http://tmw.co.uk"
					}
				],
				"meta": {
					"name" : "kickoff",
					"id": "2",
					"layout": "",
					"type": "code",
					"colours": {
						"bg": "#96C3AC",
						"text": "#1e4833",
						"link": "#F6EEDD",
						"linkHover": "#fff"
					}
				},
				"github": {
					"user": "tmwagency",
					"repo": "kickoff"
				}
			},
			{
				"name": "Javascript-less Social links",
				"description": "<p>If you've ever needed to share a web page on Facebook, Twitter, Pinterest without using each of their verbose javascript widgets, use these links instead.</p>",
				"view": {
					"name": "github.com/mrmartineau/Javascript-less-Social-Links",
					"url": "http://github.com/mrmartineau/Javascript-less-Social-Links"
				},
				"date": "Ongoing",
				"meta": {
					"name" : "javascript-less-links",
					"id": "1",
					"layout": "",
					"type": "code",
					"colours": {
						"bg": "#96C3AC",
						"text": "#1e4833",
						"link": "#F6EEDD",
						"linkHover": "#fff"
					}
				},
				"github": {
					"user": "mrmartineau",
					"repo": "Javascript-less-Social-Links"
				}
			}
		]
	},
	"sublime": {
		"title" : "Sublime Text resources",
		"description": "<p><a href=\"http://sublimetext.com\">Sublime Text</a> is my code editor of choice. It is fast, extremely extendible and I highly recommend that you use it if you are a front-end web developer. Here I present some plugins and snippets that will help to improve your experience with this code editor.</p>",
		"items": [
			{
				"name": "Sublime Text Setup",
				"description": "<p>This project aims to enable people to get started with Sublime Text 2 much more quickly. It includes a list of recommended plugins and useful defaults for some plugins and settings.</p>",
				"view": {
					"name": "github.com/mrmartineau/SublimeTextSetup",
					"url": "https://github.com/mrmartineau/SublimeTextSetup"
				},
				"date": "Ongoing",
				"meta": {
					"name" : "sublime-text-setup",
					"id": "1",
					"layout": "",
					"type": "code"
				},
				"github": {
					"user": "mrmartineau",
					"repo": "SublimeTextSetup"
				}
			},
			{
				"name": "SASS Snippets",
				"description": "<p>A collection of Sublime Text 2 snippets & functions to be used with SASS. Most snippets are to be used specifically with .scss</p>",
				"view": {
					"name": "github.com/mrmartineau/SASS-Snippets",
					"url": "https://github.com/mrmartineau/SASS-Snippets"
				},
				"date": "Ongoing",
				"meta": {
					"name" : "sass-snippets",
					"id": "1",
					"layout": "",
					"type": "code"
				},
				"github": {
					"user": "mrmartineau",
					"repo": "SASS-Snippets"
				}
			},
			{
				"name": "jQuery",
				"description": "<p>Sublime Text package bundle for jQuery. It features </p>",
				"view": {
					"name": "github.com/mrmartineau/jQuery",
					"url": "https://github.com/mrmartineau/jQuery"
				},
				"date": "Ongoing",
				"meta": {
					"name" : "jquery",
					"id": "1",
					"layout": "",
					"type": "code"
				},
				"github": {
					"user": "mrmartineau",
					"repo": "SublimeTextSetup"
				}
			},
			{
				"name": "HTML5",
				"description": "<p>HTML5 snippets library.</p>",
				"view": {
					"name": "github.com/mrmartineau/HTML5",
					"url": "https://github.com/mrmartineau/HTML5"
				},
				"date": "Ongoing",
				"meta": {
					"name" : "html5",
					"id": "1",
					"layout": "",
					"type": "code"
				},
				"github": {
					"user": "mrmartineau",
					"repo": "SublimeTextSetup"
				}
			},
			{
				"name": "Placeholders",
				"description": "<p>Placeholder HTML & content (lorem ipsum) package for Sublime Text</p>",
				"view": {
					"name": "github.com/mrmartineau/Placeholders",
					"url": "https://github.com/mrmartineau/Placeholders"
				},
				"date": "Ongoing",
				"meta": {
					"name" : "placeholders",
					"id": "1",
					"layout": "",
					"type": "code"
				},
				"github": {
					"user": "mrmartineau",
					"repo": "SublimeTextSetup"
				}
			}
		]
	},
	"cv": {
		"title": "CV",
		"statement": "I am Zander Martineau",
		"experience": [
			{
				"name": "TMW",
				"url": "http://tmw.co.uk",
				"date": "value",
				"projects": [
					{
						"name": "Knorr Mobile",
						"url": "value",
						"date": "value",
						"description": "value"
					},
					{
						"name": "Brother Printers",
						"url": "value",
						"date": "value",
						"description": "value"
					}
				]
			},
			{
				"name": "NEVERBLAND",
				"url": "http://neverbland.com",
				"date": "value",
				"projects": [
					{
						"name": "Knorr Mobile",
						"url": "value",
						"date": "value",
						"description": "value"
					},
					{
						"name": "Brother Printers",
						"url": "value",
						"date": "value",
						"description": "value"
					}
				]
			}
		]
	}
}